bhadd.py
mybhadd-0.0.1.dist-info/LICENCE.txt
mybhadd-0.0.1.dist-info/METADATA
mybhadd-0.0.1.dist-info/WHEEL
mybhadd-0.0.1.dist-info/top_level.txt
mybhadd-0.0.1.dist-info/RECORD
