Metadata-Version: 2.1
Name: mybhadd
Version: 0.0.1
Summary: test pack for addition
Classifier: Programming Language :: Python :: 3
Classifier: License :: OSI Approved :: MIT License
Classifier: Operating System :: OS Independent
License-File: LICENCE.txt
